binodcli/__init__.py
binodcli/__main__.py
binodcli/binodfile.py
binodtharu_cli-0.4.dist-info/LICENSE
binodtharu_cli-0.4.dist-info/METADATA
binodtharu_cli-0.4.dist-info/WHEEL
binodtharu_cli-0.4.dist-info/entry_points.txt
binodtharu_cli-0.4.dist-info/top_level.txt
binodtharu_cli-0.4.dist-info/RECORD
