Metadata-Version: 2.1
Name: binodtharu-cli
Version: 0.4
Summary: Binod
Home-page: https://github.com/soumya997/BinodTharu-cli
Author: Sayantan Das, Soumyadip Sarkar
Author-email: sayantandas30011998@gmail.com, soumya997.sarkar@gmail.com
License: UNKNOWN
Keywords: binod
Platform: UNKNOWN
Classifier: Programming Language :: Python :: 3
Classifier: License :: OSI Approved :: MIT License
Classifier: Operating System :: OS Independent
Requires-Python: >=3.6
License-File: LICENSE
Requires-Dist: wget
Requires-Dist: tqdm
